mtpi/__init__.py
mtpi/imaging/__init__.py
mtpi/imaging/classify.py
mtpi-0.1.7.dist-info/LICENSE
mtpi-0.1.7.dist-info/METADATA
mtpi-0.1.7.dist-info/WHEEL
mtpi-0.1.7.dist-info/top_level.txt
mtpi-0.1.7.dist-info/RECORD
