Metadata-Version: 2.1
Name: mtpi
Version: 0.1.7
Summary: A collection of utilities for data analysis.
Home-page: UNKNOWN
Author: Patrick Toohey
License: UNKNOWN
Platform: UNKNOWN
Requires-Python: >=3.7
License-File: LICENSE
Requires-Dist: pandas
Requires-Dist: matplotlib
